LSD07/1_ex/1_ex.vhd
--exercicio 1 pg. 86

library IEEE;
use ieee.std_logic_1164.all;

-- entity
entity d_ff is
    port ( S, R, D : in std_logic;
    CLK : in std_logic;
    Q, NOT_Q : out std_logic);
end d_ff;

-- architecture
architecture my_d_ff of d_ff is
begin
    dff: process (CLK)
    begin
        if (rising_edge(CLK)) then
            if (R = '1') then
                Q <= '0';
                NOT_Q <= '1';
            elsif (S = '1') then
                Q <= '1';
                NOT_Q <= '0';
            else
                Q <= D;
                NOT_Q <= NOT D;
            end if;
        end if;
    end process dff;
end my_d_ff;

LSD07/1_ex/tb_ffd.vhd
-----------------------------------------------------------
-- Model of a simple testbench to simulate a D Flip-Flop --
-----------------------------------------------------------
-- library declaration
library IEEE;
use IEEE.std_logic_1164.all;
-- top-level entity
entity tb_ffd is
end tb_ffd;

-- architecture
architecture teste of tb_ffd is
-- component declaration
component d_ff is
    port ( S, R, D : in std_logic;
            CLK : in std_logic;
            Q, NOT_Q : out std_logic);
end component;

constant PERIODO : time := 10 ns;
signal ENT_CLK : std_logic := '0'; -- deve ser inicializado
signal ENT_CLK_ENABLE: std_logic := '1'; -- Sinal de Enable do clock só para efeito de controle do fim da simulação
signal ENT_R : std_logic;
signal ENT_S : std_logic;
signal ENT_D : std_logic;
signal SAI_Q : std_logic;
signal SAI_NOT_Q : std_logic;

begin
    -- geração do clock com periodo PERIODO
    ENT_CLK <= ENT_CLK_ENABLE and not ENT_CLK after PERIODO/2;
    ENT_CLK_ENABLE <= '1', '0' after 20*PERIODO; -- a simulação termina após transcorrer 20 períodos de clock.

    -- instanciação do DUT, que nesse exemplo é um ffd
    DUT : d_ff port map(CLK => ENT_CLK,
                        R => ENT_R,
                        S => ENT_S,
                        D => ENT_D,
                        Q => SAI_Q,
                        NOT_Q => SAI_NOT_Q);
    -- a partir daqui declaro os estímulos de entrada, ou a injecao de sinais
    -- um process para o reset
    reset: process
    begin
        ENT_R <= '1';
        wait for 2*PERIODO; -- um reset de duração de 2 períodos de clock
        ENT_R <= '0';
        wait;
    end process reset;

     -- a partir daqui declaro os estímulos de entrada, ou a injecao de sinais
    -- um process para o reset
    set: process
    begin
        ENT_S <= '1';
        wait for 2*PERIODO; -- um reset de duração de 2 períodos de clock
        ENT_S <= '0';
        wait;
    end process set;    

    -- um outro process para os estímulos da entrada D
    stimulus: process
    begin
        ENT_D <= '0';
        wait for 4*PERIODO;
        ENT_D <= '1';
        wait for 6*PERIODO;
        ENT_D <= '0';
        wait for 3*PERIODO;
        ENT_D <= '1';
        wait;
    end process stimulus;
end teste;

LSD07/1_ex/tb_ffd.vcd
$date
  Mon Apr 24 20:08:41 2023
$end
$version
  GHDL v0
$end
$timescale
  1 fs
$end
$scope module standard $end
$upscope $end
$scope module std_logic_1164 $end
$upscope $end
$scope module tb_ffd $end
$var reg 1 ! ent_clk $end
$var reg 1 " ent_clk_enable $end
$var reg 1 # ent_r $end
$var reg 1 $ ent_s $end
$var reg 1 % ent_d $end
$var reg 1 & sai_q $end
$var reg 1 ' sai_not_q $end
$scope module dut $end
$var reg 1 ( s $end
$var reg 1 ) r $end
$var reg 1 * d $end
$var reg 1 + clk $end
$var reg 1 , q $end
$var reg 1 - not_q $end
$upscope $end
$upscope $end
$enddefinitions $end
#0
0!
1"
1#
1$
0%
U&
U'
1(
1)
0*
0+
U,
U-
#5000000
1!
0&
1'
1+
0,
1-
#10000000
0!
0+
#15000000
1!
1+
#20000000
0!
0#
0$
0(
0)
0+
#25000000
1!
1+
#30000000
0!
0+
#35000000
1!
1+
#40000000
0!
1%
1*
0+
#45000000
1!
1&
0'
1+
1,
0-
#50000000
0!
0+
#55000000
1!
1+
#60000000
0!
0+
#65000000
1!
1+
#70000000
0!
0+
#75000000
1!
1+
#80000000
0!
0+
#85000000
1!
1+
#90000000
0!
0+
#95000000
1!
1+
#100000000
0!
0%
0*
0+
#105000000
1!
0&
1'
1+
0,
1-
#110000000
0!
0+
#115000000
1!
1+
#120000000
0!
0+
#125000000
1!
1+
#130000000
0!
1%
1*
0+
#135000000
1!
1&
0'
1+
1,
0-
