LSD04/7_ex/if_decodificador/if_decod.vhd
--exercício 7 pg. 69
--implementar um decodificador 3x8 usando process statement 

library ieee;
use ieee.std_logic_1164.all;

--entidade decodificador 3x8
entity decod3_8 is
    port(inputs : in std_logic_vector(2 downto 0); 
        outputs : out std_logic_vector(7 downto 0) );
end decod3_8;


architecture decod3_8_if of decod3_8 is
begin
    decod_process : process(inputs) is
    begin
        if    (inputs = "000") then outputs <= "00000001";
        elsif (inputs = "001") then outputs <= "00000010";
        elsif (inputs = "010") then outputs <= "00000100";
        elsif (inputs = "011") then outputs <= "00001000";
        elsif (inputs = "100") then outputs <= "00010000";
        elsif (inputs = "101") then outputs <= "00100000";
        elsif (inputs = "110") then outputs <= "01000000";
        elsif (inputs = "111") then outputs <= "10000000";
        else outputs <= "00000000";
        end if;
    end process decod_process;
end decod3_8_if;

LSD04/7_ex/if_decodificador/tb_if_decod.vhd
--testbanch decodificador 3x8

library ieee;
use ieee.std_logic_1164.all;

entity tb_if_decod is
end tb_if_decod;

architecture tb_decod3_8 of tb_if_decod is
    component decod3_8 is
        port(inputs : in std_logic_vector(2 downto 0); 
            outputs : out std_logic_vector(7 downto 0) );
    end component;

signal inputs: std_logic_vector(2 downto 0);
signal outputs: std_logic_vector(7 downto 0);

begin
    instancia: decod3_8 port map(inputs => inputs, outputs => outputs);
    inputs <= "000", "001" after 10 ns, "010" after 20 ns, "011" after 30 ns,
    "100" after 40 ns, "101" after 50 ns, "110" after 60 ns, "111" after 70 ns;

end tb_decod3_8;

LSD04/7_ex/if_decodificador/tb_if_decod.vcd
$date
  Sun Apr 02 22:18:54 2023
$end
$version
  GHDL v0
$end
$timescale
  1 fs
$end
$scope module standard $end
$upscope $end
$scope module std_logic_1164 $end
$upscope $end
$scope module tb_if_decod $end
$var reg 3 ! inputs[2:0] $end
$var reg 8 " outputs[7:0] $end
$scope module instancia $end
$var reg 3 # inputs[2:0] $end
$var reg 8 $ outputs[7:0] $end
$upscope $end
$upscope $end
$enddefinitions $end
#0
b000 !
b00000001 "
b000 #
b00000001 $
#10000000
b001 !
b00000010 "
b001 #
b00000010 $
#20000000
b010 !
b00000100 "
b010 #
b00000100 $
#30000000
b011 !
b00001000 "
b011 #
b00001000 $
#40000000
b100 !
b00010000 "
b100 #
b00010000 $
#50000000
b101 !
b00100000 "
b101 #
b00100000 $
#60000000
b110 !
b01000000 "
b110 #
b01000000 $
#70000000
b111 !
b10000000 "
b111 #
b10000000 $
