my_projects/parte_pratica/funcao.vhd
-- ULA

library ieee;
use ieee.std_logic_1164.all;
use ieee.numeric_std.all;

entity ULA is
  port(A, B : in std_logic_vector(7 downto 0);
		   ULA_SEL : in std_logic_vector(2 downto 0);
       ULA_OUT : out std_logic_vector(7 downto 0));
end ULA;

architecture funcao of ULA is
  begin
    my_proc : process(A, B, ULA_SEL)
    begin
      case(ULA_SEL) is
        when "001" => ULA_OUT <= std_logic_vector(signed(A) + signed(B)); -- Soma com sinal
        when "010" => ULA_OUT <= std_logic_vector(unsigned(A) + unsigned(B)); -- Soma sem sinal
        when "011" => ULA_OUT <= std_logic_vector(unsigned(A) - unsigned(B)); -- Subtração
        when "100" => ULA_OUT <= A or B;  -- OR lógico
        when "101" => ULA_OUT <= A and B; -- AND lógico
        when "110" => ULA_OUT <= A xor B; -- XOR lógico
        when others => ULA_OUT <= "00000000";
      end case;
    end process my_proc;
end funcao;

my_projects/parte_pratica/tb_funcao.vhd
-- Testbench da ULA

library ieee;
use ieee.std_logic_1164.all;

entity tb_funcao is
end tb_funcao;

architecture teste of tb_funcao is
  component ULA is
    port(A, B : in std_logic_vector(7 downto 0);
         ULA_SEL : in std_logic_vector(2 downto 0);
         ULA_OUT : out std_logic_vector(7 downto 0));
  end component;

  signal a, b : std_logic_vector(7 downto 0);
  signal ula_sel : std_logic_vector(2 downto 0);
  signal ula_out : std_logic_vector(7 downto 0);
  
  begin
    instancia : ULA port map(A => a, B => b, ULA_SEL => ula_sel, ULA_OUT => ula_out);
    a <= "00000000", "11111111" after 35 ns;
    b <= "11111111", "00000000" after 35 ns;
    ula_sel <= "000", "001" after 10 ns, "010" after 20 ns, "011" after 30 ns,    
           "100" after 40 ns, "101" after 50 ns, "110" after 60 ns, "111" after 70 ns;
end teste;

my_projects/parte_pratica/tb_funcao.vcd
$date
  Mon Apr 10 06:09:39 2023
$end
$version
  GHDL v0
$end
$timescale
  1 fs
$end
$scope module standard $end
$upscope $end
$scope module std_logic_1164 $end
$upscope $end
$scope module numeric_std $end
$upscope $end
$scope module tb_funcao $end
$var reg 8 ! a[7:0] $end
$var reg 8 " b[7:0] $end
$var reg 3 # ula_sel[2:0] $end
$var reg 8 $ ula_out[7:0] $end
$scope module instancia $end
$var reg 8 % a[7:0] $end
$var reg 8 & b[7:0] $end
$var reg 3 ' ula_sel[2:0] $end
$var reg 8 ( ula_out[7:0] $end
$upscope $end
$upscope $end
$enddefinitions $end
#0
b00000000 !
b11111111 "
b000 #
b00000000 $
b00000000 %
b11111111 &
b000 '
b00000000 (
#10000000
b001 #
b11111111 $
b001 '
b11111111 (
#20000000
b010 #
b010 '
#30000000
b011 #
b00000001 $
b011 '
b00000001 (
#35000000
b11111111 !
b00000000 "
b11111111 $
b11111111 %
b00000000 &
b11111111 (
#40000000
b100 #
b100 '
#50000000
b101 #
b00000000 $
b101 '
b00000000 (
#60000000
b110 #
b11111111 $
b110 '
b11111111 (
#70000000
b111 #
b00000000 $
b111 '
b00000000 (
