LSD07/mean-4-clocks-master/mean_4_clocks.vhd
-- mean_4_clocks - A system that calculates the mean over four clocks
-- Copyright (C) 2018  Digital Systems Group - UFMG
-- 
-- This program is free software; you can redistribute it and/or modify
-- it under the terms of the GNU General Public License as published by
-- the Free Software Foundation; either version 3 of the License, or
-- (at your option) any later version.
-- 
-- This program is distributed in the hope that it will be useful,
-- but WITHOUT ANY WARRANTY; without even the implied warranty of
-- MERCHANTABILITY or FITNESS FOR A PARTICULAR PURPOSE.  See the
-- GNU General Public License for more details.
-- 
-- You should have received a copy of the GNU General Public License
-- along with this program; if not, see <https://www.gnu.org/licenses/>.
--

library ieee;
use ieee.std_logic_1164.all;
use ieee.numeric_std.all;

entity mean_4_clocks is
    generic (
        W       :       integer := 32
    );
    port (
        CLK     : in    std_logic;
        RESET   : in    std_logic;
        INPUT   : in    std_logic_vector(W - 1 downto 0);
        OUTPUT  : out   std_logic_vector(W - 1 downto 0)
    );
end mean_4_clocks;

-- Implement the testbench and find the errors in this model.
-- Consider the following expected behavior:
--      Every rising edge of CLK input, the content of INPUT
--      is added to a register chain and used to calculate the
--      mean value over 4 clock periods

architecture arch of mean_4_clocks is
begin
    process(CLK, RESET) is
        variable var1 : unsigned(W - 1 downto 0);
        variable var2 : unsigned(W - 1 downto 0);
        variable var3 : unsigned(W - 1 downto 0);
        variable var4 : unsigned(W - 1 downto 0);
    begin
        if (RESET = '1') then
            var1 := to_unsigned(0,W);
            var2 := to_unsigned(0,W);
            var3 := to_unsigned(0,W);
            var4 := to_unsigned(0,W);
        elsif (rising_edge(CLK)) then 
            var4 := var3;
            var3 := var2;
            var2 := var1;
            var1 := unsigned(INPUT(W-1 downto 0));
        end if;
        
        OUTPUT <= std_logic_vector((var1 + var2 + var3 + var4) srl 2);
    end process;
    
end arch;

LSD07/mean-4-clocks-master/tb_mean_4_clocks.vhd
-----------------------------------------------------------
-- Model of a simple testbench to simulate a D Flip-Flop --
-----------------------------------------------------------
-- library declaration
library IEEE;
use IEEE.std_logic_1164.all;
-- top-level entity
entity tb_mean_4_clocks is
end tb_mean_4_clocks;

-- architecture
architecture tb_architecture of tb_mean_4_clocks is
    -- component declaration
    component mean_4_clocks is
        generic (
            W       :       integer := 32
        );
        port (
            CLK     : in    std_logic;
            RESET   : in    std_logic;
            INPUT   : in    std_logic_vector(W - 1 downto 0);
            OUTPUT  : out   std_logic_vector(W - 1 downto 0)
        );
end component;

constant PERIODO : time := 10 ns;
signal ENT_CLK : std_logic := '0'; -- deve ser inicializado
signal ENT_CLK_ENABLE: std_logic := '1'; -- Sinal de Enable do clock só para efeito de controle do fim da simulação
signal ENT_R : std_logic;
signal ENT_INPUT : std_logic_vector(32 - 1 downto 0);
signal SAI_Q : std_logic_vector(32 - 1 downto 0);

begin
    -- geração do clock com periodo PERIODO
    ENT_CLK <= ENT_CLK_ENABLE and not ENT_CLK after PERIODO/2;
    ENT_CLK_ENABLE <= '1', '0' after 20*PERIODO; -- a simulação termina após transcorrer 20 períodos de clock.

    -- instanciação do DUT, que nesse exemplo é um ffd
    DUT : mean_4_clocks port map(
                        CLK => ENT_CLK,
                        RESET => ENT_R,
                        INPUT => ENT_INPUT,
                        OUTPUT => SAI_Q);

    -- a partir daqui declaro os estímulos de entrada, ou a injecao de sinais
    -- um process para o reset
    reset: process
    begin
        ENT_R <= '1';
        wait for 2*PERIODO; -- um reset de duração de 2 períodos de clock
        ENT_R <= '0';
        wait;
    end process reset;

    -- um outro process para os estímulos da entrada D
    stimulus: process
    begin
        ENT_INPUT <= "00000000000000000000000000000000";
        wait for 4*PERIODO;
        ENT_INPUT <= "00000000000000000000000000000001";
        wait for 6*PERIODO;
        ENT_INPUT <= "00000000000000000000000000000100";
        wait for 3*PERIODO;
        ENT_INPUT <= "00000000000000000000000000100000";
        wait;
    end process stimulus;
end tb_architecture;

LSD07/mean-4-clocks-master/tb_mean_4_clocks.vcd
$date
  Mon Apr 24 22:08:07 2023
$end
$version
  GHDL v0
$end
$timescale
  1 fs
$end
$scope module standard $end
$upscope $end
$scope module std_logic_1164 $end
$upscope $end
$scope module numeric_std $end
$upscope $end
$scope module tb_mean_4_clocks $end
$var reg 1 ! ent_clk $end
$var reg 1 " ent_clk_enable $end
$var reg 1 # ent_r $end
$var reg 32 $ ent_input[31:0] $end
$var reg 32 % sai_q[31:0] $end
$scope module dut $end
$var reg 1 & clk $end
$var reg 1 ' reset $end
$var reg 32 ( input[31:0] $end
$var reg 32 ) output[31:0] $end
$upscope $end
$upscope $end
$enddefinitions $end
#0
0!
1"
1#
b00000000000000000000000000000000 $
b00000000000000000000000000000000 %
0&
1'
b00000000000000000000000000000000 (
b00000000000000000000000000000000 )
#5000000
1!
1&
#10000000
0!
0&
#15000000
1!
1&
#20000000
0!
0#
0&
0'
#25000000
1!
1&
#30000000
0!
0&
#35000000
1!
1&
#40000000
0!
b00000000000000000000000000000001 $
0&
b00000000000000000000000000000001 (
#45000000
1!
1&
#50000000
0!
0&
#55000000
1!
1&
#60000000
0!
0&
#65000000
1!
1&
#70000000
0!
0&
#75000000
1!
b00000000000000000000000000000001 %
1&
b00000000000000000000000000000001 )
#80000000
0!
0&
#85000000
1!
1&
#90000000
0!
0&
#95000000
1!
1&
#100000000
0!
b00000000000000000000000000000100 $
0&
b00000000000000000000000000000100 (
#105000000
1!
1&
#110000000
0!
0&
#115000000
1!
b00000000000000000000000000000010 %
1&
b00000000000000000000000000000010 )
#120000000
0!
0&
#125000000
1!
b00000000000000000000000000000011 %
1&
b00000000000000000000000000000011 )
#130000000
0!
b00000000000000000000000000100000 $
0&
b00000000000000000000000000100000 (
#135000000
1!
b00000000000000000000000000001011 %
1&
b00000000000000000000000000001011 )
#140000000
0!
0&
#145000000
1!
b00000000000000000000000000010010 %
1&
b00000000000000000000000000010010 )
#150000000
0!
0&
#155000000
1!
b00000000000000000000000000011001 %
1&
b00000000000000000000000000011001 )
#160000000
0!
0&
#165000000
1!
b00000000000000000000000000100000 %
1&
b00000000000000000000000000100000 )
